massive_serve/__init__.py
massive_serve/cli.py
massive_serve/data_utils.py
massive_serve/api/__init__.py
massive_serve/api/api_index.py
massive_serve/api/serve.py
massive_serve/api/__pycache__/__init__.cpython-310.pyc
massive_serve/api/__pycache__/__init__.cpython-312.pyc
massive_serve/api/__pycache__/api_index.cpython-312.pyc
massive_serve/api/__pycache__/serve.cpython-310.pyc
massive_serve/api/__pycache__/serve.cpython-312.pyc
massive_serve/contriever/__init__.py
massive_serve/contriever/src/contriever.py
massive_serve/contriever/src/dist_utils.py
massive_serve/contriever/src/utils.py
massive_serve/src/__init__.py
massive_serve/src/data.py
massive_serve/src/search.py
massive_serve/src/indicies/base.py
massive_serve/src/indicies/flat.py
massive_serve/src/indicies/ivf_flat.py
massive_serve/src/indicies/ivf_pq.py
massive_serve-0.1.20.dist-info/METADATA
massive_serve-0.1.20.dist-info/WHEEL
massive_serve-0.1.20.dist-info/entry_points.txt
massive_serve-0.1.20.dist-info/top_level.txt
massive_serve-0.1.20.dist-info/RECORD
