Metadata-Version: 2.4
Name: massive_serve
Version: 0.1.20
Summary: A package for massive serving
Home-page: https://github.com/RulinShao/massive-serve
Author: Rulin Shao
Author-email: rulins@cs.washington.edu
Classifier: Programming Language :: Python :: 3
Classifier: License :: OSI Approved :: MIT License
Classifier: Operating System :: OS Independent
Requires-Python: >=3.7
Requires-Dist: click
Requires-Dist: tqdm
Requires-Dist: flask
Requires-Dist: flask-cors
Requires-Dist: torch
Requires-Dist: transformers
Requires-Dist: numpy
Requires-Dist: sentence-transformers
Requires-Dist: faiss-cpu
Provides-Extra: cpu
Requires-Dist: faiss-cpu; extra == "cpu"
Provides-Extra: gpu
Requires-Dist: faiss-gpu; extra == "gpu"
Dynamic: author
Dynamic: author-email
Dynamic: classifier
Dynamic: description
Dynamic: description-content-type
Dynamic: home-page
Dynamic: provides-extra
Dynamic: requires-dist
Dynamic: requires-python
Dynamic: summary
